{
  "meta": {
    "honap": "2026 június",
    "frissitve": "2026-06-11"
  },
  "franchise": [
    "Miskolc",
    "Pécs"
  ],
  "levonasok": [],
  "uzletek": [
    {
      "nev": "Király utca",
      "leltar_pct": 99.78,
      "osszes": -16553,
      "gomboc": 2704,
      "ital": -7230,
      "desseg": -3897,
      "doboz": -5700,
      "snack": -2430,
      "ajandek": 0,
      "selejt_pct": 7.7
    },
    {
      "nev": "Fashion",
      "leltar_pct": 100.25,
      "osszes": 10874,
      "gomboc": 10744,
      "ital": 1280,
      "desseg": 0,
      "doboz": -1150,
      "snack": 0,
      "ajandek": 0,
      "selejt_pct": 11.7
    },
    {
      "nev": "Bazilika",
      "leltar_pct": 99.1,
      "osszes": -39260,
      "gomboc": -42681,
      "ital": 14660,
      "desseg": -1299,
      "doboz": -8550,
      "snack": -1390,
      "ajandek": 0,
      "selejt_pct": 9.1
    },
    {
      "nev": "Széll Kálmán",
      "leltar_pct": 99.58,
      "osszes": -21861,
      "gomboc": -22002,
      "ital": 740,
      "desseg": -1299,
      "doboz": 700,
      "snack": 0,
      "ajandek": 0,
      "selejt_pct": 4.6
    },
    {
      "nev": "Corvin",
      "leltar_pct": 99.41,
      "osszes": -14588,
      "gomboc": -989,
      "ital": -650,
      "desseg": -1299,
      "doboz": -12250,
      "snack": 600,
      "ajandek": 0,
      "selejt_pct": 6.0
    },
    {
      "nev": "Károly krt",
      "leltar_pct": 98.8,
      "osszes": -47127,
      "gomboc": -21667,
      "ital": -4360,
      "desseg": 0,
      "doboz": -21100,
      "snack": 0,
      "ajandek": 0,
      "selejt_pct": 8.1
    },
    {
      "nev": "Dob",
      "leltar_pct": 99.49,
      "osszes": -16691,
      "gomboc": -14451,
      "ital": -3290,
      "desseg": 0,
      "doboz": -750,
      "snack": 1800,
      "ajandek": 0,
      "selejt_pct": 6.6
    },
    {
      "nev": "Blaha",
      "leltar_pct": 100.11,
      "osszes": 6895,
      "gomboc": 464,
      "ital": -8420,
      "desseg": -1299,
      "doboz": 15550,
      "snack": 600,
      "ajandek": 0,
      "selejt_pct": 6.6
    },
    {
      "nev": "Oktogon",
      "leltar_pct": 100.1,
      "osszes": 10359,
      "gomboc": 13620,
      "ital": -3870,
      "desseg": 1299,
      "doboz": 0,
      "snack": -1190,
      "ajandek": 500,
      "selejt_pct": 10.5
    },
    {
      "nev": "Wesselényi",
      "leltar_pct": 100.24,
      "osszes": 14150,
      "gomboc": 2441,
      "ital": 10670,
      "desseg": 1299,
      "doboz": -2650,
      "snack": 2390,
      "ajandek": 0,
      "selejt_pct": 4.9
    },
    {
      "nev": "Astoria",
      "leltar_pct": 98.11,
      "osszes": -61291,
      "gomboc": -29631,
      "ital": -6720,
      "desseg": 0,
      "doboz": -5750,
      "snack": -18590,
      "ajandek": -600,
      "selejt_pct": 14.2
    },
    {
      "nev": "Erzsébet krt 14",
      "leltar_pct": 100.1,
      "osszes": 6108,
      "gomboc": 10158,
      "ital": -5590,
      "desseg": 0,
      "doboz": 600,
      "snack": 1190,
      "ajandek": -250,
      "selejt_pct": 15.4
    },
    {
      "nev": "Gomba Móricz",
      "leltar_pct": 99.7,
      "osszes": -22533,
      "gomboc": -15562,
      "ital": -7320,
      "desseg": 1299,
      "doboz": -1050,
      "snack": 0,
      "ajandek": 100,
      "selejt_pct": 8.8
    },
    {
      "nev": "Keleti",
      "leltar_pct": 100.1,
      "osszes": 10809,
      "gomboc": 16869,
      "ital": -1780,
      "desseg": 0,
      "doboz": -1100,
      "snack": -3180,
      "ajandek": 0,
      "selejt_pct": 8.6
    },
    {
      "nev": "Fővám tér",
      "leltar_pct": 99.32,
      "osszes": -23036,
      "gomboc": -14946,
      "ital": -7040,
      "desseg": 0,
      "doboz": 150,
      "snack": -1200,
      "ajandek": 0,
      "selejt_pct": 8.8
    },
    {
      "nev": "Ferenciek tere",
      "leltar_pct": 100.1,
      "osszes": 9626,
      "gomboc": 7186,
      "ital": 3290,
      "desseg": 0,
      "doboz": -2050,
      "snack": 1200,
      "ajandek": 0,
      "selejt_pct": 7.3
    },
    {
      "nev": "Jászai Mari tér",
      "leltar_pct": 100.1,
      "osszes": 5777,
      "gomboc": 2667,
      "ital": 2970,
      "desseg": 0,
      "doboz": -850,
      "snack": 0,
      "ajandek": 990,
      "selejt_pct": 11.9
    },
    {
      "nev": "Etele",
      "leltar_pct": 99.65,
      "osszes": -17534,
      "gomboc": -15505,
      "ital": -4530,
      "desseg": -1299,
      "doboz": 3350,
      "snack": 0,
      "ajandek": 450,
      "selejt_pct": 11.6
    },
    {
      "nev": "Kispest",
      "leltar_pct": 99.8,
      "osszes": -3212,
      "gomboc": 818,
      "ital": -7720,
      "desseg": 0,
      "doboz": 0,
      "snack": 3590,
      "ajandek": 100,
      "selejt_pct": 0
    },
    {
      "nev": "Bosnyák tér",
      "leltar_pct": 99.8,
      "osszes": 2170,
      "gomboc": 15890,
      "ital": -5720,
      "desseg": 0,
      "doboz": -10250,
      "snack": 1200,
      "ajandek": 1050,
      "selejt_pct": 12.4
    },
    {
      "nev": "Árkád",
      "leltar_pct": 100.1,
      "osszes": 5513,
      "gomboc": 16153,
      "ital": -1890,
      "desseg": 0,
      "doboz": -8850,
      "snack": 0,
      "ajandek": 100,
      "selejt_pct": 10.6
    },
    {
      "nev": "Kazinczy",
      "leltar_pct": 100.3,
      "osszes": 26718,
      "gomboc": 15318,
      "ital": 4880,
      "desseg": 0,
      "doboz": -2700,
      "snack": 9220,
      "ajandek": 0,
      "selejt_pct": 8.8
    },
    {
      "nev": "Törökvész",
      "leltar_pct": 99.9,
      "osszes": -3024,
      "gomboc": -234,
      "ital": -190,
      "desseg": 0,
      "doboz": -3800,
      "snack": 600,
      "ajandek": 600,
      "selejt_pct": 7.7
    },
    {
      "nev": "GO Buda",
      "leltar_pct": 100.1,
      "osszes": 21892,
      "gomboc": 21332,
      "ital": -1980,
      "desseg": 0,
      "doboz": -1650,
      "snack": 3790,
      "ajandek": 400,
      "selejt_pct": 13.4
    },
    {
      "nev": "D1 Buda",
      "leltar_pct": 99.1,
      "osszes": -40059,
      "gomboc": -9769,
      "ital": -29300,
      "desseg": 0,
      "doboz": 0,
      "snack": -1190,
      "ajandek": 200,
      "selejt_pct": 3.5
    },
    {
      "nev": "D2 Baross",
      "leltar_pct": 99.8,
      "osszes": -5339,
      "gomboc": -8029,
      "ital": -1230,
      "desseg": 1990,
      "doboz": 0,
      "snack": 2380,
      "ajandek": -450,
      "selejt_pct": 7.4
    },
    {
      "nev": "Újpest",
      "leltar_pct": 100.1,
      "osszes": -165,
      "gomboc": 1924,
      "ital": -1190,
      "desseg": -1299,
      "doboz": 0,
      "snack": 0,
      "ajandek": 400,
      "selejt_pct": 0
    },
    {
      "nev": "K1 Westend",
      "leltar_pct": 100.3,
      "osszes": 8780,
      "gomboc": 13230,
      "ital": -4850,
      "desseg": 0,
      "doboz": 400,
      "snack": 0,
      "ajandek": 0,
      "selejt_pct": 14.6
    },
    {
      "nev": "BP PARK",
      "leltar_pct": 99.5,
      "osszes": -19744,
      "gomboc": -18644,
      "ital": 0,
      "desseg": 0,
      "doboz": -1100,
      "snack": 0,
      "ajandek": 0,
      "selejt_pct": 8.9
    },
    {
      "nev": "PLázs",
      "leltar_pct": 99.5,
      "osszes": -23348,
      "gomboc": -23738,
      "ital": 390,
      "desseg": 0,
      "doboz": 0,
      "snack": 0,
      "ajandek": 0,
      "selejt_pct": 19.6
    },
    {
      "nev": "F1 Siófok",
      "leltar_pct": 99.5,
      "osszes": -28716,
      "gomboc": -10926,
      "ital": -15690,
      "desseg": 0,
      "doboz": -2100,
      "snack": 0,
      "ajandek": 0,
      "selejt_pct": 15.8
    },
    {
      "nev": "Szeged",
      "leltar_pct": 99.5,
      "osszes": -13480,
      "gomboc": -30031,
      "ital": 31620,
      "desseg": 4671,
      "doboz": -1550,
      "snack": -18790,
      "ajandek": 600,
      "selejt_pct": 13.9
    },
    {
      "nev": "Pécs",
      "leltar_pct": 99.7,
      "osszes": -13905,
      "gomboc": -1775,
      "ital": -9990,
      "desseg": 0,
      "doboz": -2150,
      "snack": -4580,
      "ajandek": 4590,
      "selejt_pct": 5.5,
      "franchise": true
    },
    {
      "nev": "Miskolc",
      "leltar_pct": 100.2,
      "osszes": 19414,
      "gomboc": 7498,
      "ital": 9840,
      "desseg": 1526,
      "doboz": 0,
      "snack": 0,
      "ajandek": 550,
      "selejt_pct": 0,
      "franchise": true
    }
  ],
  "trend": {
    "Király utca": {
      "2023": {
        "avg": -75323,
        "h": [
          -57924,
          -15652,
          -79554,
          -116099,
          -98329,
          -16056,
          -146223,
          -95346,
          -71937,
          -54859,
          -76971,
          -74926
        ]
      },
      "2024": {
        "avg": -57390,
        "h": [
          -65448,
          -89962,
          -21475,
          -2956,
          -23768,
          -57038,
          -110019,
          -73175,
          -117236,
          -50714,
          -26464,
          -50422
        ]
      },
      "2025": {
        "avg": -50783,
        "h": [
          -58986,
          -42884,
          -53649,
          -38338,
          -42313,
          -79073,
          -130655,
          -90480,
          -43402,
          -2990,
          -28268,
          1643
        ]
      }
    },
    "Fashion": {
      "2023": {
        "avg": -100435,
        "h": [
          -63689,
          -69756,
          -100745,
          -81803,
          -50697,
          -168075,
          -40766,
          -196245,
          -182961,
          -99850,
          -135921,
          -14715
        ]
      },
      "2024": {
        "avg": -29719,
        "h": [
          -21637,
          -25749,
          -49171,
          -75204,
          -63405,
          -38567,
          -31298,
          4399,
          -15788,
          -14744,
          -26017,
          555
        ]
      },
      "2025": {
        "avg": -2963,
        "h": [
          -1238,
          -10206,
          -33470,
          6074,
          -15162,
          28809,
          -1999,
          -6749,
          12896,
          5336,
          -5750,
          -14102
        ]
      }
    },
    "Corvin": {
      "2023": {
        "avg": -21519,
        "h": [
          101809,
          -38460,
          -126515,
          -76697,
          20667,
          -800,
          -46897,
          -25546,
          -25081,
          -17390,
          -68580,
          45266
        ]
      },
      "2024": {
        "avg": -11732,
        "h": [
          5721,
          -43037,
          -38423,
          -29024,
          -34349,
          -1392,
          -5049,
          -30855,
          24105,
          -3551,
          -2140,
          17213
        ]
      },
      "2025": {
        "avg": 17177,
        "h": [
          17352,
          25279,
          11958,
          16445,
          51808,
          43495,
          13952,
          -6332,
          29758,
          27222,
          6510,
          -31326
        ]
      }
    },
    "Keleti": {
      "2023": {
        "avg": -53605,
        "h": [
          -46725,
          5603,
          -43929,
          -94308,
          -40191,
          -46598,
          -50600,
          -77803,
          -99028,
          -20537,
          -43365,
          -85774
        ]
      },
      "2024": {
        "avg": -29092,
        "h": [
          -12651,
          10926,
          -40982,
          -11739,
          -23375,
          -19547,
          -35049,
          -56008,
          -48257,
          -16473,
          -71802,
          -24152
        ]
      },
      "2025": {
        "avg": -21815,
        "h": [
          -29586,
          3433,
          -27285,
          -1235,
          -80071,
          -84833,
          20465,
          -11019,
          -10963,
          -30879,
          21550,
          -31353
        ]
      }
    },
    "Astoria": {
      "2023": {
        "avg": -37678,
        "h": [
          -177240,
          -1579,
          -34328,
          -29286,
          -36226,
          -74524,
          -72725,
          8191,
          2356,
          -3732,
          -28856,
          -4187
        ]
      },
      "2024": {
        "avg": -13098,
        "h": [
          -1548,
          -10797,
          -7099,
          -7055,
          -7602,
          5340,
          -3118,
          3074,
          -100505,
          -4070,
          -9241,
          1614
        ]
      },
      "2025": {
        "avg": -20042,
        "h": [
          -30338,
          -21278,
          -7462,
          -9305,
          -24188,
          -6613,
          -6687,
          -60757,
          -5250,
          -25087,
          23249,
          -66784
        ]
      }
    }
  }
}